pyCritical/__init__.py
pyCritical/src/__init__.py
pyCritical/src/cpm_pert.py
pycritical-1.7.2.dist-info/LICENSE
pycritical-1.7.2.dist-info/METADATA
pycritical-1.7.2.dist-info/WHEEL
pycritical-1.7.2.dist-info/top_level.txt
pycritical-1.7.2.dist-info/zip-safe
pycritical-1.7.2.dist-info/RECORD
