Metadata-Version: 2.1
Name: pycritical
Version: 1.7.2
Summary: A Python Library for CPM and PERT Methods
Home-page: https://github.com/Valdecy/pyCritical
Author: Valdecy Pereira
Author-email: valdecy.pereira@gmail.com
License: GNU
License-File: LICENSE
Requires-Dist: matplotlib
Requires-Dist: numpy
Requires-Dist: pandas
Requires-Dist: scipy
